euphonium/__init__.py
euphonium/euphonium.py
euphonium-0.0.1.dist-info/LICENSE
euphonium-0.0.1.dist-info/METADATA
euphonium-0.0.1.dist-info/WHEEL
euphonium-0.0.1.dist-info/top_level.txt
euphonium-0.0.1.dist-info/RECORD
