Metadata-Version: 2.1
Name: euphonium
Version: 0.0.1
Summary: Contemporary Python Utilities for Deep Learning Applications
Home-page: https://github.com/void-echo/euphonium
Author: Echo Void
Author-email: void-echo@outlook.com
Classifier: Programming Language :: Python :: 3
Classifier: License :: OSI Approved :: MIT License
Classifier: Operating System :: OS Independent
License-File: LICENSE
Requires-Dist: requests
